{"cameraMode":{"drawMode":0,"name":"Shaded","section":"Shading Mode"},"sceneLighting":true,"audioPlay":false,"sceneViewState":{"m_AlwaysRefresh":false,"showFog":true,"showSkybox":true,"showFlares":true,"showImageEffects":true,"showParticleSystems":true,"showVisualEffectGraphs":true,"m_FxEnabled":true},"in2DMode":false,"pivot":{"x":261.6275329589844,"y":17.085786819458009,"z":282.5440368652344},"rotation":{"x":0.015220067463815213,"y":-0.3440851867198944,"z":0.0055751679465174679,"w":0.938823938369751},"size":1.3449110984802247,"orthographic":false}